{"counter":3,"\n{\\setlength{\\GGlinewidth}{53pt}\n \\setlength{\\GGthickness}{1pt}\n \\setlength{\\GGbeforelen}{5pt}\n \\setlength{\\GGafterlen}{5pt}\n\\GGjudge\\GGall{a}\\GGconditional\n  {\\GGterm{F(\\mathfrak{a})}}\n  {\\GGconditional{\\GGnot\\GGterm{G(\\mathfrak{a})}}\n  {\\GGterm{F(\\mathfrak{a})}}}}\n":{"display":{"svg":"images/fregeify1.svg"}},"\n\\pmthm \\pmdottt \\pmsome{f} \\pmdottt \\pmall{x, y} \\pmdott \\phi(x, y) \\pmdot\\pmiff\\pmdot \\pmpredd{f}{x}{y} \\pmdot\n":{"display":{"svg":"images/fregeify2.svg"}},"\\pmsome{x}\\pmdot\\pmpred{\\phi}x":{"inline":{"svg":"images/fregeify3.svg"}}}